{
  "required": true,
  "$schema": "http://json-schema.org/draft-03/schema",
  "type": "object",
  "properties": {
    "associatedActions": {
      "type": "object",
      "required": false,
      "properties": {"actionLinkGroupIds": {
        "type": "array",
        "required": false
      }}
    },
    "bookmarks": {
      "type": "object",
      "required": false,
      "properties": {"isBookmarkedByCurrentUser": {
        "type": "boolean",
        "required": false
      }}
    },
    "canvas": {
      "type": "object",
      "required": false,
      "properties": {
        "description": {
          "type": "string",
          "required": false
        },
        "developerName": {
          "type": "string",
          "required": false
        },
        "height": {
          "type": "string",
          "required": false
        },
        "namespacePrefix": {
          "type": "string",
          "required": false
        },
        "parameters": {
          "type": "string",
          "required": false
        },
        "thumbnailUrl": {
          "type": "string",
          "required": false
        },
        "title": {
          "type": "string",
          "required": false
        }
      }
    },
    "content": {
      "type": "object",
      "required": false,
      "properties": {
        "contentDocumentId": {
          "type": "string",
          "required": false
        },
        "description": {
          "type": "string",
          "required": false
        },
        "title": {
          "type": "string",
          "required": false
        }
      }
    },
    "link": {
      "type": "object",
      "required": false,
      "properties": {
        "url": {
          "type": "string",
          "required": false
        },
        "urlName": {
          "type": "string",
          "required": false
        }
      }
    },
    "poll": {
      "type": "object",
      "required": false,
      "properties": {
        "choices": {
          "type": "array",
          "required": false
        },
        "myChoiceId": {
          "type": "string",
          "required": false
        }
      }
    },
    "questionAndAnswers": {
      "type": "object",
      "required": false,
      "properties": {
        "bestAnswerId": {
          "type": "string",
          "required": false
        },
        "questionTitle": {
          "type": "string",
          "required": false
        }
      }
    }
  }
}