{
  "required" : true ,
  "$schema" : "http://json-schema.org/draft-03/schema" ,
  "type" : "array" ,
  "items" : [
    {
      "type" : "object" ,
      "properties" : {
        "id" : {
          "type" : "number" ,
          "required" : false
        } ,
        "name" : {
          "type" : "string" ,
          "required" : false
        } ,
        "owner" : {
          "type" : "string" ,
          "required" : false
        } ,
        "ownerId" : {
          "type" : "number" ,
          "required" : false
        }
      }
    }
  ]
}